mojopack/__init__.py
mojopack/mojopack.py
mojopack-0.1.dist-info/LICENSE
mojopack-0.1.dist-info/METADATA
mojopack-0.1.dist-info/WHEEL
mojopack-0.1.dist-info/entry_points.txt
mojopack-0.1.dist-info/top_level.txt
mojopack-0.1.dist-info/RECORD
