Metadata-Version: 2.1
Name: mojopack
Version: 0.1
Summary: mojopack is a tool for managing packages for the Mojo programming language.
Home-page: https://github.com/kernhanda/mojopack
Author: Kern Handa
Author-email: kern.handa@gmail.com
Classifier: Development Status :: 3 - Alpha
Classifier: Intended Audience :: Developers
Classifier: License :: OSI Approved :: MIT License
Classifier: Programming Language :: Python :: 3
Classifier: Programming Language :: Python :: 3.8
Classifier: Programming Language :: Python :: 3.9
Classifier: Programming Language :: Python :: 3.10
Classifier: Programming Language :: Python :: 3.11
Requires-Python: >=3.8
License-File: LICENSE
Requires-Dist: requests >=2.26.0
Requires-Dist: tqdm >=4.62.0
